corut_installer/__init__.py
corut_installer/installer.py
corut_installer-0.0.19.dist-info/LICENSE
corut_installer-0.0.19.dist-info/METADATA
corut_installer-0.0.19.dist-info/WHEEL
corut_installer-0.0.19.dist-info/top_level.txt
corut_installer-0.0.19.dist-info/RECORD
