Metadata-Version: 2.1
Name: corut-installer
Version: 0.0.19
Summary: Makes the necessary installations for python on Linux/Windows systems with GUI
Home-page: https://pypi.org/project/corut_installer/
Author: ibrahim CÖRÜT
Author-email: ibrhmcorut@gmail.com
License: MIT License
Project-URL: Documentation, https://www.ibrahimcorut.com/en/projects/pypi-corut-installer/
Project-URL: Source Code, https://www.ibrahimcorut.com/en/projects/pypi-corut-installer/
Keywords: cörüt, corut, corut_installer, installer
Classifier: Intended Audience :: Developers
Classifier: License :: OSI Approved :: MIT License
Classifier: Operating System :: OS Independent
Classifier: Programming Language :: Python :: 3
Classifier: Programming Language :: Python :: 3 :: Only
Classifier: Programming Language :: Python :: 3.7
Classifier: Programming Language :: Python :: 3.8
Classifier: Programming Language :: Python :: 3.9
Classifier: Programming Language :: Python :: 3.10
Requires-Python: >=3.7
License-File: LICENSE
Requires-Dist: importlib-metadata
